pdm_bump-0.9.12.dist-info/METADATA
pdm_bump-0.9.12.dist-info/WHEEL
pdm_bump-0.9.12.dist-info/entry_points.txt
pdm_bump-0.9.12.dist-info/licenses/LICENSE
pdm_bump/__init__.py
pdm_bump/actions/__init__.py
pdm_bump/actions/base.py
pdm_bump/actions/explicit.py
pdm_bump/actions/hook.py
pdm_bump/actions/increment.py
pdm_bump/actions/poetry_like.py
pdm_bump/actions/preview.py
pdm_bump/actions/vcs.py
pdm_bump/actions/version_providers.py
pdm_bump/cli.py
pdm_bump/core/__init__.py
pdm_bump/core/config.py
pdm_bump/core/version.py
pdm_bump/plugin.py
pdm_bump/py.typed
pdm_bump/storage.py
pdm_bump/vcs/__init__.py
pdm_bump/vcs/core.py
pdm_bump/vcs/git.py
pdm_bump/vcs/gitcli.py
pdm_bump/vcs/history.py
pdm_bump-0.9.12.dist-info/RECORD
