Metadata-Version: 2.4
Name: pdm-bump
Version: 0.9.12
Summary: A plugin for PDM providing the ability to modify the version according to PEP440
Author-Email: Carsten Igel <cig@bite-that-bit.de>
License-Expression: MIT
License-File: LICENSE
Project-URL: homepage, https://github.com/carstencodes/pdm-bump
Requires-Python: >=3.9
Requires-Dist: pdm>=2.22.4
Requires-Dist: annotated-types>=0.7.0
Requires-Dist: typing-extensions>=4.12.2; python_version <= "3.9"
Requires-Dist: tomlkit>=0.13.2
Requires-Dist: tomli>=2.2.1; python_version <= "3.10"
Requires-Dist: pyproject-metadata>=0.9.1
Requires-Dist: pdm-pfsc>=0.12.3
